Metadata-Version: 2.1
Name: ZamoGaussianDistribution
Version: 0.2
Summary: Gaussian distributions
Author: Zamokwakhe Mthethwa
Author-email: cihle.zm.01@gmail.com
